{
    "agenix": {
        "branch": "main",
        "description": "age-encrypted secrets for NixOS",
        "homepage": "https://matrix.to/#/#agenix:nixos.org",
        "owner": "ryantm",
        "repo": "agenix",
        "rev": "a630400067c6d03c9b3e0455347dc8559db14288",
        "sha256": "04i8qiy71shv42jzxhwfzqpzm1l46q6d5qgjl17dq36bdrpymijf",
        "type": "tarball",
        "url": "https://github.com/ryantm/agenix/archive/a630400067c6d03c9b3e0455347dc8559db14288.tar.gz",
        "url_template": "https://github.com/<owner>/<repo>/archive/<rev>.tar.gz"
    },
    "home-manager": {
        "branch": "release-22.11",
        "description": "Manage a user environment using Nix  [maintainer=@rycee] ",
        "homepage": "https://nix-community.github.io/home-manager/",
        "owner": "nix-community",
        "repo": "home-manager",
        "rev": "0e8125916b420e41bf0d23a0aa33fadd0328beb3",
        "sha256": "1pcdmkw9azg2w3jxpw8xw6qak7bilaf8mdasn8rc8vl5iz5lilpy",
        "type": "tarball",
        "url": "https://github.com/nix-community/home-manager/archive/0e8125916b420e41bf0d23a0aa33fadd0328beb3.tar.gz",
        "url_template": "https://github.com/<owner>/<repo>/archive/<rev>.tar.gz"
    },
    "nixos-stable": {
        "branch": "nixos-22.11",
        "description": "Nix Packages collection",
        "homepage": "",
        "owner": "NixOS",
        "repo": "nixpkgs",
        "rev": "cbe419ed4c8f98bd82d169c321d339ea30904f1f",
        "sha256": "0l6lipg37mzpajiik2rlm4whm53xn3bi0317wdqdwip8dz30sj1h",
        "type": "tarball",
        "url": "https://github.com/NixOS/nixpkgs/archive/cbe419ed4c8f98bd82d169c321d339ea30904f1f.tar.gz",
        "url_template": "https://github.com/<owner>/<repo>/archive/<rev>.tar.gz"
    },
    "nixos-unstable": {
        "branch": "nixos-unstable",
        "description": "Nix Packages collection",
        "homepage": "",
        "owner": "NixOS",
        "repo": "nixpkgs",
        "rev": "04f574a1c0fde90b51bf68198e2297ca4e7cccf4",
        "sha256": "1frf2yspkgy72c5pznjgk8hbla7yyrn78azsf3ypkyb84vml5jnw",
        "type": "tarball",
        "url": "https://github.com/NixOS/nixpkgs/archive/04f574a1c0fde90b51bf68198e2297ca4e7cccf4.tar.gz",
        "url_template": "https://github.com/<owner>/<repo>/archive/<rev>.tar.gz"
    }
}
